gosound/__init__.py
gosound/core.py
gosound-0.1.3.dist-info/METADATA
gosound-0.1.3.dist-info/WHEEL
gosound-0.1.3.dist-info/entry_points.txt
gosound-0.1.3.dist-info/top_level.txt
gosound-0.1.3.dist-info/RECORD
