Metadata-Version: 2.4
Name: GoSound
Version: 0.1.3
Summary: A short description of my awesome library.
Author: 王子毅
License: MIT
Keywords: easy,pygame,play-audio
Classifier: License :: OSI Approved :: MIT License
Classifier: Programming Language :: Python :: 3
Classifier: Programming Language :: Python :: 3.7
Classifier: Programming Language :: Python :: 3.8
Classifier: Programming Language :: Python :: 3.9
Classifier: Programming Language :: Python :: 3.10
Classifier: Programming Language :: Python :: 3.11
Classifier: Operating System :: OS Independent
Requires-Dist: pygame
